jinja2_td-3.1.6.post1.dist-info/licenses/LICENSE_JINJA2
jinja2td/__init__.py
jinja2td/dependencies.py
jinja2td/introspection.py
jinja2td/overrides.py
jinja2td/py.typed
jinja2_td-3.1.6.post1.dist-info/METADATA
jinja2_td-3.1.6.post1.dist-info/WHEEL
jinja2_td-3.1.6.post1.dist-info/top_level.txt
jinja2_td-3.1.6.post1.dist-info/RECORD
