Metadata-Version: 2.4
Name: Jinja2-TD
Version: 3.1.6.post1
Summary: Jinja2 template dependency insight
Home-page: https://github.com/louisdevie/jinja2-td
Author: Louis DEVIE
License: MIT
Keywords: jinja,jinja2,template,dependency
Classifier: Development Status :: 5 - Production/Stable
Classifier: Programming Language :: Python :: 3.8
Requires-Python: >=3.8
License-File: LICENSE_JINJA2
Requires-Dist: Jinja2<=3.1.6,>=3.1.5
Dynamic: author
Dynamic: classifier
Dynamic: description
Dynamic: description-content-type
Dynamic: home-page
Dynamic: keywords
Dynamic: license
Dynamic: license-file
Dynamic: requires-dist
Dynamic: requires-python
Dynamic: summary
